xwebetl/__init__.py
xwebetl/cli/__init__.py
xwebetl/cli/main.py
xwebetl/extract/__init__.py
xwebetl/extract/dispatch.py
xwebetl/extract/http.py
xwebetl/extract/rss.py
xwebetl/extract/tests/test_dispatch.py
xwebetl/load/__init__.py
xwebetl/load/load.py
xwebetl/load/tests/test_load.py
xwebetl/source/__init__.py
xwebetl/source/base_processor.py
xwebetl/source/data_manager.py
xwebetl/source/source_manager.py
xwebetl/source/tests/__init__.py
xwebetl/source/tests/test_source_manager.py
xwebetl/transform/__init__.py
xwebetl/transform/transform.py
xwebetl/transform/tests/test_transform.py
xwebetl-0.1.4.dist-info/licenses/LICENSE
xwebetl-0.1.4.dist-info/METADATA
xwebetl-0.1.4.dist-info/WHEEL
xwebetl-0.1.4.dist-info/entry_points.txt
xwebetl-0.1.4.dist-info/top_level.txt
xwebetl-0.1.4.dist-info/RECORD
