Metadata-Version: 2.4
Name: xwebetl
Version: 0.1.4
Summary: A flexible web content extraction, transformation, and loading (ETL) pipeline
Author-email: ObergXData <obergxdata@gmail.com>
Project-URL: Homepage, https://github.com/obergxdata/WebETL
Project-URL: Documentation, https://github.com/obergxdata/WebETL#readme
Project-URL: Repository, https://github.com/obergxdata/WebETL
Project-URL: Issues, https://github.com/obergxdata/WebETL/issues
Keywords: rss,web scraping,etl,data pipeline,content extraction
Classifier: Development Status :: 3 - Alpha
Classifier: Intended Audience :: Developers
Classifier: License :: OSI Approved :: MIT License
Classifier: Programming Language :: Python :: 3
Classifier: Programming Language :: Python :: 3.11
Classifier: Programming Language :: Python :: 3.12
Classifier: Topic :: Software Development :: Libraries :: Python Modules
Classifier: Topic :: Internet :: WWW/HTTP :: Dynamic Content
Requires-Python: >=3.11
License-File: LICENSE
Requires-Dist: lxml>=4.9.0
Requires-Dist: requests>=2.31.0
Requires-Dist: feedparser>=6.0.0
Requires-Dist: PyYAML>=6.0
Requires-Dist: openai>=1.0.0
Requires-Dist: pypdfium2>=3.0.0
Requires-Dist: click>=8.0.0
Provides-Extra: dev
Requires-Dist: pytest>=7.4.0; extra == "dev"
Requires-Dist: pytest-mock>=3.11.0; extra == "dev"
Dynamic: license-file
